{"is_source_file": true, "format": "JavaScript", "description": "React component implementing a sign-in page with form validation, styling, and navigation logic.", "external_files": ["../context/AuthContext", "../RouterApp", "./signin.common.css"], "external_methods": ["useAuth.signIn", "navigate"], "published": ["default"], "classes": [], "methods": [{"name": "SignIn()", "description": "React functional component rendering a sign-in form with validation and submit handler.", "scope": "", "scopeKind": ""}, {"name": "onSubmit", "description": "Handles form submission, performs validation, calls signIn, and navigates upon success."}], "calls": ["useAuth", "navigate", "setEmail", "setPassword", "setSubmitting", "setError", "signIn", "navigate"], "search-terms": ["SignIn React component", "SignIn form", "useAuth context", "navigate function", "sign-in validation"], "state": 2, "file_id": 24, "knowledge_revision": 159, "git_revision": "b2b1ecb7739af95cebdddd04bdb7cbf29e85c5cc", "revision_history": [{"52": ""}, {"63": "02b455d8bc5ffbfff58ebe9ff628416afc72c538"}, {"74": "24a049246ccf5db68c2611dcffdca2068b56cfe7"}, {"105": "50e57f94e0817b23ae813743d143d2873075f99a"}, {"128": "f241d8e811ff0b2bdc1a3773c4702f8562252fc9"}, {"136": "2927d82ac1ab2c1bc92a05045639ec57ee7c171c"}, {"159": "b2b1ecb7739af95cebdddd04bdb7cbf29e85c5cc"}], "ctags": [{"_type": "tag", "name": "SignIn", "path": "/home/kavia/workspace/code-generation/recipe-explorer-183463-183512/recipe_app_frontend/src/pages/SignIn.js", "pattern": "/^export default function SignIn() {$/", "language": "JavaScript", "kind": "function", "signature": "()"}, {"_type": "tag", "name": "email", "path": "/home/kavia/workspace/code-generation/recipe-explorer-183463-183512/recipe_app_frontend/src/pages/SignIn.js", "pattern": "/^            value={email}$/", "language": "JavaScript", "kind": "field", "scope": "value", "scopeKind": "class"}, {"_type": "tag", "name": "onSubmit", "path": "/home/kavia/workspace/code-generation/recipe-explorer-183463-183512/recipe_app_frontend/src/pages/SignIn.js", "pattern": "/^        onSubmit={onSubmit}$/", "language": "JavaScript", "kind": "field", "scope": "SignIn.onSubmit", "scopeKind": "class"}, {"_type": "tag", "name": "password", "path": "/home/kavia/workspace/code-generation/recipe-explorer-183463-183512/recipe_app_frontend/src/pages/SignIn.js", "pattern": "/^            value={password}$/", "language": "JavaScript", "kind": "field", "scope": "value", "scopeKind": "class"}, {"_type": "tag", "name": "submitting", "path": "/home/kavia/workspace/code-generation/recipe-explorer-183463-183512/recipe_app_frontend/src/pages/SignIn.js", "pattern": "/^          disabled={submitting}$/", "language": "JavaScript", "kind": "field", "scope": "disabled", "scopeKind": "class"}], "hash": "27ddb4472b7f4506a0ecc7afa696d879", "format-version": 4, "code-base-name": "recipe_app_frontend", "filename": "recipe_app_frontend/src/pages/SignIn.js", "fields": [{"name": "value={email}", "scope": "value", "scopeKind": "class", "description": "unavailable"}, {"name": "onSubmit={onSubmit}", "scope": "SignIn.onSubmit", "scopeKind": "class", "description": "unavailable"}, {"name": "value={password}", "scope": "value", "scopeKind": "class", "description": "unavailable"}, {"name": "disabled={submitting}", "scope": "disabled", "scopeKind": "class", "description": "unavailable"}]}